odoo/addons/stock_picking_batch_extended_account/README.rst
odoo/addons/stock_picking_batch_extended_account/__init__.py
odoo/addons/stock_picking_batch_extended_account/__manifest__.py
odoo/addons/stock_picking_batch_extended_account/i18n/stock_picking_batch_extended_account.pot
odoo/addons/stock_picking_batch_extended_account/models/__init__.py
odoo/addons/stock_picking_batch_extended_account/models/res_partner.py
odoo/addons/stock_picking_batch_extended_account/models/stock_batch_picking.py
odoo/addons/stock_picking_batch_extended_account/models/stock_picking.py
odoo/addons/stock_picking_batch_extended_account/readme/CONFIGURE.rst
odoo/addons/stock_picking_batch_extended_account/readme/CONTRIBUTORS.rst
odoo/addons/stock_picking_batch_extended_account/readme/DESCRIPTION.rst
odoo/addons/stock_picking_batch_extended_account/readme/USAGE.rst
odoo/addons/stock_picking_batch_extended_account/static/description/icon.png
odoo/addons/stock_picking_batch_extended_account/static/description/index.html
odoo/addons/stock_picking_batch_extended_account/views/res_partner_views.xml
odoo/addons/stock_picking_batch_extended_account/views/stock_batch_picking.xml
odoo12_addon_stock_picking_batch_extended_account-12.0.1.0.0.99.dev3.dist-info/METADATA
odoo12_addon_stock_picking_batch_extended_account-12.0.1.0.0.99.dev3.dist-info/WHEEL
odoo12_addon_stock_picking_batch_extended_account-12.0.1.0.0.99.dev3.dist-info/top_level.txt
odoo12_addon_stock_picking_batch_extended_account-12.0.1.0.0.99.dev3.dist-info/RECORD
